gtkmvc3/__init__.py
gtkmvc3/controller.py
gtkmvc3/model.py
gtkmvc3/model_mt.py
gtkmvc3/observable.py
gtkmvc3/observer.py
gtkmvc3/view.py
gtkmvc3/adapters/__init__.py
gtkmvc3/adapters/basic.py
gtkmvc3/adapters/containers.py
gtkmvc3/adapters/default.py
gtkmvc3/progen/__init__.py
gtkmvc3/progen/ctrl.py
gtkmvc3/progen/globals.py
gtkmvc3/progen/model.py
gtkmvc3/progen/progen.ui
gtkmvc3/progen/templates.py
gtkmvc3/progen/view.py
gtkmvc3/support/__init__.py
gtkmvc3/support/decorators.py
gtkmvc3/support/exceptions.py
gtkmvc3/support/factories.py
gtkmvc3/support/log.py
gtkmvc3/support/metaclasses.py
gtkmvc3/support/noconflict.py
gtkmvc3/support/options.py
gtkmvc3/support/porting.py
gtkmvc3/support/utils.py
gtkmvc3/support/wrappers.py
python_gtkmvc3_dlr-1.0.0.data/scripts/gtkmvc3-progen
python_gtkmvc3_dlr-1.0.0.dist-info/DESCRIPTION.rst
python_gtkmvc3_dlr-1.0.0.dist-info/METADATA
python_gtkmvc3_dlr-1.0.0.dist-info/RECORD
python_gtkmvc3_dlr-1.0.0.dist-info/WHEEL
python_gtkmvc3_dlr-1.0.0.dist-info/metadata.json
python_gtkmvc3_dlr-1.0.0.dist-info/top_level.txt
