Metadata-Version: 2.0
Name: python-gtkmvc3-dlr
Version: 1.0.0
Summary: Model-View-Controller and Observer patterns for developing pygtk-based applications
Home-page: https://github.com/roboogle/gtkmvc3/
Author: Roberto Cavada, Sebastian Brunner, Rico Belder, Franz Steinmetz
Author-email: roboogle@gmail.com
Maintainer: Sebastian Brunner
Maintainer-email: sebastian.brunner@dlr.de
License: LGPL
Keywords: mvc
Platform: UNKNOWN
Classifier: Development Status :: 4 - Beta
Classifier: Environment :: Console
Classifier: Environment :: X11 Applications :: GTK
Classifier: Intended Audience :: Developers
Classifier: License :: OSI Approved :: GNU Library or Lesser General Public License (LGPL)
Classifier: Operating System :: MacOS :: MacOS X
Classifier: Operating System :: Microsoft :: Windows
Classifier: Operating System :: POSIX
Classifier: Programming Language :: Python :: 2
Classifier: Programming Language :: Python :: 3
Classifier: Topic :: Software Development :: User Interfaces
Classifier: Topic :: Software Development :: Libraries :: Application Frameworks
